bitpay/__init__.py
bitpay/bitpay_client.py
bitpay/bitpay_exceptions.py
bitpay/bitpay_key_utils.py
globee_py2-2.3.5.dist-info/DESCRIPTION.rst
globee_py2-2.3.5.dist-info/METADATA
globee_py2-2.3.5.dist-info/RECORD
globee_py2-2.3.5.dist-info/WHEEL
globee_py2-2.3.5.dist-info/metadata.json
globee_py2-2.3.5.dist-info/top_level.txt
